gqylpy_cache/__init__.py
gqylpy_cache/g cache.py
gqylpy_cache-1.3.4.dist-info/LICENSE
gqylpy_cache-1.3.4.dist-info/METADATA
gqylpy_cache-1.3.4.dist-info/WHEEL
gqylpy_cache-1.3.4.dist-info/top_level.txt
gqylpy_cache-1.3.4.dist-info/RECORD
